LICENSE.txt
README.md
setup.cfg
setup.py
pyEager/__init__.py
pyEager/parsers.py
pyEager/wrappers.py
pyEager.egg-info/PKG-INFO
pyEager.egg-info/SOURCES.txt
pyEager.egg-info/dependency_links.txt
pyEager.egg-info/requires.txt
pyEager.egg-info/top_level.txt