Metadata-Version: 2.1
Name: pyEager
Version: 0.1.6.1
Summary: A simple package to read in eager results.
Home-page: https://github.com/TCLamnidis/pyEager
Download-URL: https://github.com/TCLamnidis/pyEager/archive/refs/tags/0.1.6.1.tar.gz
Author: Thiseas C. Lamnidis
Author-email: thisseass@gmail.com
License: MIT
Keywords: python,pandas,nf-core,eager,nf-core/eager,ancient DNA
Classifier: Development Status :: 3 - Alpha
Classifier: License :: OSI Approved :: MIT License
Classifier: Programming Language :: Python :: 3
Classifier: Programming Language :: Python :: 3.4
Classifier: Programming Language :: Python :: 3.5
Classifier: Programming Language :: Python :: 3.6
Classifier: Programming Language :: Python :: 3.7
Classifier: Programming Language :: Python :: 3.8
Classifier: Programming Language :: Python :: 3.9
Requires-Python: >=3.6
License-File: LICENSE.txt
Requires-Dist: pandas
Requires-Dist: numpy
